odoo/addons/auth_admin_passkey/README.rst
odoo/addons/auth_admin_passkey/__init__.py
odoo/addons/auth_admin_passkey/__manifest__.py
odoo/addons/auth_admin_passkey/i18n/ar.po
odoo/addons/auth_admin_passkey/i18n/auth_admin_passkey.pot
odoo/addons/auth_admin_passkey/i18n/ca.po
odoo/addons/auth_admin_passkey/i18n/da.po
odoo/addons/auth_admin_passkey/i18n/de.po
odoo/addons/auth_admin_passkey/i18n/el_GR.po
odoo/addons/auth_admin_passkey/i18n/es.po
odoo/addons/auth_admin_passkey/i18n/es_ES.po
odoo/addons/auth_admin_passkey/i18n/fi.po
odoo/addons/auth_admin_passkey/i18n/fr.po
odoo/addons/auth_admin_passkey/i18n/fr_CH.po
odoo/addons/auth_admin_passkey/i18n/fr_FR.po
odoo/addons/auth_admin_passkey/i18n/hr.po
odoo/addons/auth_admin_passkey/i18n/hr_HR.po
odoo/addons/auth_admin_passkey/i18n/it.po
odoo/addons/auth_admin_passkey/i18n/nl.po
odoo/addons/auth_admin_passkey/i18n/nl_NL.po
odoo/addons/auth_admin_passkey/i18n/pt.po
odoo/addons/auth_admin_passkey/i18n/pt_BR.po
odoo/addons/auth_admin_passkey/i18n/ro.po
odoo/addons/auth_admin_passkey/i18n/sl.po
odoo/addons/auth_admin_passkey/i18n/tr.po
odoo/addons/auth_admin_passkey/i18n/tr_TR.po
odoo/addons/auth_admin_passkey/i18n/zh_CN.po
odoo/addons/auth_admin_passkey/models/__init__.py
odoo/addons/auth_admin_passkey/models/res_users.py
odoo/addons/auth_admin_passkey/readme/CONFIGURE.md
odoo/addons/auth_admin_passkey/readme/CONTRIBUTORS.md
odoo/addons/auth_admin_passkey/readme/DESCRIPTION.md
odoo/addons/auth_admin_passkey/static/description/icon.png
odoo/addons/auth_admin_passkey/static/description/index.html
odoo/addons/auth_admin_passkey/tests/__init__.py
odoo/addons/auth_admin_passkey/tests/test_auth_admin_passkey.py
odoo/addons/auth_admin_passkey/tests/test_ui.py
odoo_addon_auth_admin_passkey-18.0.1.0.0.3.dist-info/METADATA
odoo_addon_auth_admin_passkey-18.0.1.0.0.3.dist-info/WHEEL
odoo_addon_auth_admin_passkey-18.0.1.0.0.3.dist-info/top_level.txt
odoo_addon_auth_admin_passkey-18.0.1.0.0.3.dist-info/RECORD
